[{"Name":"Trello","BestFor":"Simple task tracking","Complexity":"Very easy","Pros":"✔️ Intuitive UI, Templates, Mobile app","Cons":"❌ Limited for complex workflows","Scalability":"Limited","Training":"No learning curve","Affiliate":"✅ [link](https://trello.com/affiliates)","Link":"https://trello.com/","Logo":"trello-logo.png","Rating":"9.8/10","Category":"task","FreePlan":"Free forever up to 10 users","PaidPlan":"$5/user/mo"},{"Name":"ClickUp","BestFor":"Power users, scaleable","Complexity":"Elevated","Pros":"✔️ Custom views, Automation, Docs","Cons":"❌ Overwhelming for newbies","Scalability":"High","Training":"Medium learning curve","Affiliate":"✅ [link](https://clickup.com/partners)","Link":"https://clickup.com/","Logo":"clickup-logo.png","Rating":"9.2/10","Category":"task,project","FreePlan":"Free forever up to 10 users","PaidPlan":"$5/user/mo"},{"Name":"Taskade","BestFor":"Minimalist team tasks","Complexity":"Easy","Pros":"✔️ Real-time sync, Clean UI, Templates","Cons":"❌ Limited integrations","Scalability":"Medium","Training":"Almost none","Affiliate":"✅ [link](https://www.taskade.com/partners)","Link":"https://www.taskade.com/","Logo":"todoist-logo.png","Rating":"8.8/10","Category":"notes","FreePlan":"Free forever up to 10 users","PaidPlan":"$5/user/mo"},{"Name":"Notion","BestFor":"All-in-one workspace","Complexity":"Moderate","Pros":"✔️ Flexible, Database power, Beautiful","Cons":"❌ Confusing for newbies","Scalability":"Very high","Training":"Requires learning","Affiliate":"✅ [link](https://notion.grsm.io/)","Link":"https://notion.so/","Logo":"notion-logo.png","Rating":"8.4/10","Category":"task,project,notes","FreePlan":"Free forever up to 10 users","PaidPlan":"$5/user/mo"},{"Name":"Asana","BestFor":"Collaboration & reporting","Complexity":"Easy","Pros":"✔️ Project templates, Timeline, Teams","Cons":"❌ Less customizable","Scalability":"High","Training":"Minimal","Affiliate":"✅ [link](https://asana.grsm.io/)","Link":"https://asana.com/","Logo":"asana-logo.png","Rating":"7.9/10","Category":"project,task","FreePlan":"Free forever up to 10 users","PaidPlan":"$5/user/mo"}]
